dicom2stl/Dicom2STL.py
dicom2stl/__init__.py
dicom2stl/utils/__init__.py
dicom2stl/utils/dicomutils.py
dicom2stl/utils/parseargs.py
dicom2stl/utils/regularize.py
dicom2stl/utils/sitk2vtk.py
dicom2stl/utils/vtk2sitk.py
dicom2stl/utils/vtkutils.py
dicom2stl-0.5.0.dist-info/LICENSE.txt
dicom2stl-0.5.0.dist-info/METADATA
dicom2stl-0.5.0.dist-info/WHEEL
dicom2stl-0.5.0.dist-info/entry_points.txt
dicom2stl-0.5.0.dist-info/top_level.txt
dicom2stl-0.5.0.dist-info/RECORD
