Metadata-Version: 2.1
Name: dicom2stl
Version: 0.5.0
Summary: A script to extract an iso-surface from a DICOM series to produce an STL mesh.
Author-email: David Chen <dchen@mail.nih.gov>
Project-URL: Homepage, https://github.com/dave3d/dicom2stl
Project-URL: Bug Tracker, https://github.com/dave3d/dicom2stl
Classifier: Programming Language :: Python :: 3
Classifier: License :: OSI Approved :: MIT License
Classifier: Operating System :: OS Independent
Requires-Python: >=3.8
License-File: LICENSE.txt
Requires-Dist: numpy >=1.24.0
Requires-Dist: SimpleITK >=2.2.1
Requires-Dist: vtk >=9.2.0
Requires-Dist: pydicom >=2.3
Requires-Dist: simpleitkutilities >=0.3.0
